colab_ssh/__init__.py
colab_ssh/config.py
colab_ssh/main.py
colab_ssh/notification.py
colab_ssh/progress_bar.py
colab_ssh/ssh.py
colab_ssh/tunel.py
colab_ssh/utils.py
linus_colab_ssh-0.1.6.dist-info/LICENSE
linus_colab_ssh-0.1.6.dist-info/METADATA
linus_colab_ssh-0.1.6.dist-info/WHEEL
linus_colab_ssh-0.1.6.dist-info/top_level.txt
linus_colab_ssh-0.1.6.dist-info/RECORD
