Metadata-Version: 2.1
Name: linus-colab-ssh
Version: 0.1.6
Summary: Create SSH tunel to a running colab notebook
Home-page: https://github.com/lamhoangtung/colab_ssh
Author: Hoang Tung Lam
Author-email: lamhoangtung.vz@gmail.com
License: UNKNOWN
Keywords: ssh,colab
Platform: UNKNOWN
Classifier: Intended Audience :: Developers
Classifier: Topic :: Software Development :: Libraries
Classifier: License :: OSI Approved :: MIT License
Classifier: Programming Language :: Python :: 3.6
Classifier: Programming Language :: Python :: 3.7
Classifier: Programming Language :: Python :: 3.8
Classifier: Programming Language :: Python :: 3.9
Requires-Python: >=3
License-File: LICENSE
